{
  "name": "PriceEdge",
  "//topbarLinks": [
    {
      "name": "Login",
      "url": "https://priceedge.eu/login"
    }
  ],
  "topbarCtaButton": {
    "name": "Login",
    "url": "https://priceedge.eu/login"
  },
  "//tabs": [
    {
      "name": "API Reference",
      "url": "api-reference"
    }
  ],
  "colors":{
    "primary": "#E7556A",
    "dark":"#E7556A",
    "light":"#E7556A"
  },

  "anchors": [
    {
        "name": "Quick Start",
        "icon": "bolt",
        "url": "api-references"
    },
    {
        "name": "API Documentation",
        "icon": "terminal",
        "url": "content"
    },
    {
        "name": "FAQ",
        "icon": "question",
        "url": "faq"
    }
],

"favicon": "/favicon.svg",

"topAnchor": {
  "name": "Overview",
  "icon": "poo-storm"
},



  "navigation": [
    {
      "group": "Overview",
      "pages": ["introduction"]
    },
    {
      "group": "Quick Start",
      "pages": ["quickstart/quickstart-1", "quickstart/quickstart-2", "quickstart/quickstart-3"]
    },
    {
      "group": "API Documentation",
      "pages": ["api-reference/authentication"]
    },
    {
      "group": "Endpoint Examples",
      "pages": [
        "api-reference/endpoint/get",
        "api-reference/endpoint/create",
        "api-reference/endpoint/update",
        "api-reference/endpoint/delete"
      ]
    }
  ],
  "footerSocials": {
    "twitter": "https://twitter.com/mintlify",
    "github": "https://github.com/mintlify",
    "linkedin": "https://www.linkedin.com/company/mintsearch"
  },
  "backgroundImage": "/background.png"
}
